Metadata-Version: 1.0
Name: RecordSilo
Version: 0.4
Summary: An adaptation of a pairtree store, each object with simple JSON keyvalue manifest and crude versioning.
Home-page: UNKNOWN
Author: Ben O'Steen
Author-email: bosteen@gmail.com
License: UNKNOWN
Platform: UNKNOWN
